requests_tor.py
requests_tor-1.4.dist-info/LICENSE
requests_tor-1.4.dist-info/METADATA
requests_tor-1.4.dist-info/WHEEL
requests_tor-1.4.dist-info/top_level.txt
requests_tor-1.4.dist-info/RECORD
