Metadata-Version: 2.1
Name: requests-tor
Version: 1.4
Summary: Multithreading requests via TOR with automatic TOR new identity
Home-page: https://github.com/deedy5/requests_tor
Author: deedy5
Author-email: 
License: MIT
Classifier: Development Status :: 5 - Production/Stable
Classifier: License :: OSI Approved :: MIT License
Classifier: Operating System :: OS Independent
Classifier: Programming Language :: Python :: 3
Classifier: Programming Language :: Python :: 3 :: Only
Classifier: Programming Language :: Python :: 3.7
Classifier: Programming Language :: Python :: 3.8
Classifier: Programming Language :: Python :: 3.9
Classifier: Programming Language :: Python :: 3.10
Classifier: Programming Language :: Python :: 3.11
Classifier: Programming Language :: Python :: Implementation :: CPython
Requires-Python: >=3.6
License-File: LICENSE
